constants.py
ai_assistant_multi-1.0.0.dist-info/licenses/LICENSE
commands/__init__.py
commands/session_cmd.py
commands/setup_cmd.py
core/__init__.py
core/chat_session.py
utils/__init__.py
utils/base_client.py
utils/config_manager.py
utils/google_client.py
utils/openai_client.py
utils/session_manager.py
ai_assistant_multi-1.0.0.dist-info/METADATA
ai_assistant_multi-1.0.0.dist-info/WHEEL
ai_assistant_multi-1.0.0.dist-info/entry_points.txt
ai_assistant_multi-1.0.0.dist-info/top_level.txt
ai_assistant_multi-1.0.0.dist-info/RECORD
