Metadata-Version: 2.4
Name: ai-assistant-multi
Version: 1.0.0
Summary: A multi-provider CLI assistant for interacting with AI models (OpenAI, Google Gemini).
Author-email: Sudharshan V <sudarshan61kv@gmail.com>
License-Expression: MIT
Project-URL: Homepage, https://github.com/Sudharshan1409/assistant-cli
Project-URL: Repository, https://github.com/Sudharshan1409/assistant-cli
Keywords: ai,assistant,cli,gemini,gpt,llm,multi-provider,openai,terminal
Classifier: Development Status :: 4 - Beta
Classifier: Environment :: Console
Classifier: Intended Audience :: Developers
Classifier: Intended Audience :: End Users/Desktop
Classifier: Operating System :: OS Independent
Classifier: Programming Language :: Python :: 3 :: Only
Classifier: Programming Language :: Python :: 3.8
Classifier: Programming Language :: Python :: 3.9
Classifier: Programming Language :: Python :: 3.10
Classifier: Programming Language :: Python :: 3.11
Classifier: Programming Language :: Python :: 3.12
Classifier: Programming Language :: Python :: 3.13
Classifier: Topic :: Scientific/Engineering :: Artificial Intelligence
Classifier: Topic :: Utilities
Requires-Python: >=3.8
License-File: LICENSE
Requires-Dist: google-generativeai>=0.8.5
Requires-Dist: openai>=1.75
Requires-Dist: questionary>=2.1
Requires-Dist: rich>=14
Requires-Dist: typer[all]>=0.15.2
Dynamic: license-file
